qplot/CSV.py
qplot/K_Component.py
qplot/K_Netze.py
qplot/M_CSV.py
qplot/M_DataAnalysis.py
qplot/PosFind.py
qplot/bounding_boxes.py
qplot/color_schema.py
qplot/cursor.py
qplot/geojson_export.py
qplot/plot_map.py
qplot/plot_objects.py
qplot/qplot.py
qplot/wheels.py
qplot/data/TM_WORLD_BORDERS-0.3.shp
qplot/packages/__init__.py
qplot/packages/bounding_boxes.py
qplot/packages/color_schema.py
qplot/packages/cursor.py
qplot/packages/plot_map.py
qplot/packages/plot_objects.py
qplot/packages/wheels.py
qplot-1.1.1.dist-info/LICENSE
qplot-1.1.1.dist-info/METADATA
qplot-1.1.1.dist-info/WHEEL
qplot-1.1.1.dist-info/top_level.txt
qplot-1.1.1.dist-info/RECORD
