Metadata-Version: 2.1
Name: qplot
Version: 1.1.1
Summary: Visualization of SciGRID_gas networks structures
Home-page: https://github.com/pypa/qplot
Author: Adam Pluta
Author-email: Adam.Pluta@dlr.de
License: UNKNOWN
Platform: UNKNOWN
Classifier: License :: OSI Approved :: GNU General Public License v3 or later (GPLv3+)
Classifier: Programming Language :: Python :: 3
Classifier: Programming Language :: Python :: 3.6
Requires-Python: >=3.6
License-File: LICENSE
Requires-Dist: matplotlib (==3.4.0)
Requires-Dist: mplcursors (>=0.4)
Requires-Dist: PyShp
Requires-Dist: pandas (>=0.25.3)
Requires-Dist: numpy (==1.19.4)
Requires-Dist: pathlib (>=1.0.1)
Requires-Dist: descartes (==1.1.0)
Requires-Dist: adjustText (==0.7.3)
Requires-Dist: Unidecode (==1.1.1)
Requires-Dist: Shapely (==1.7.1)
